{"learner":{"attributes":{"scikit_learn":"{\"_estimator_type\": \"classifier\"}"},"feature_names":["bias_week","bias_month","bias_quarter","bias_year","rsi","macd","macd_signal","vol_change","close_change","bb_width","return_5d","k_upper","k_lower","k_body","buy_power","rs_5d"],"feature_types":["float","float","float","float","float","float","float","float","float","float","float","float","float","float","float","float"],"gradient_booster":{"model":{"cats":{"enc":[],"feature_segments":[],"sorted_idx":[]},"gbtree_model_param":{"num_parallel_tree":"1","num_trees":"21"},"iteration_indptr":[0,1,2,3,4,5,6,7,8,9,10,11,12,13,14,15,16,17,18,19,20,21],"tree_info":[0,0,0,0,0,0,0,0,0,0,0,0,0,0,0,0,0,0,0,0,0],"trees":[{"base_weights":[3.7036662E-3,7.310711E-2,-7.453492E-2,-1.4205141E-1,8.322494E-2,-2.8946951E-2,8.235309E-3],"categories":[],"categories_nodes":[],"categories_segments":[],"categories_sizes":[],"default_left":[0,0,0,0,0,0,0],"id":0,"left_children":[1,-1,3,5,-1,-1,-1],"loss_changes":[1.8407436E1,0E0,1.4697507E1,8.826183E0,0E0,0E0,0E0],"parents":[2147483647,0,0,2,2,3,3],"right_children":[2,-1,4,6,-1,-1,-1],"split_conditions":[-2.435659E-1,7.310711E-2,4.7690654E0,5.946562E-3,8.322494E-2,-2.8946951E-2,8.235309E-3],"split_indices":[3,0,6,0,0,0,0],"split_type":[0,0,0,0,0,0,0],"sum_hessian":[2.9467307E2,3.1125E1,2.6354807E2,2.4776923E2,1.5778847E1,1.5477885E2,9.299039E1],"tree_param":{"num_deleted":"0","num_feature":"16","num_nodes":"7","size_leaf_vector":"1"}},{"base_weights":[1.621109E-2,-7.382042E-2,6.209536E-2,-1.9590868E-2,2.108332E-1,-0E0,4.1819744E-2],"categories":[],"categories_nodes":[],"categories_segments":[],"categories_sizes":[],"default_left":[0,0,0,0,0,0,0],"id":1,"left_children":[1,3,-1,-1,5,-1,-1],"loss_changes":[1.7364824E1,8.8672495E0,0E0,0E0,3.7721403E0,0E0,0E0],"parents":[2147483647,0,0,1,1,4,4],"right_children":[2,4,-1,-1,6,-1,-1],"split_conditions":[7.325068E-2,1.0396717E-1,6.209536E-2,-1.9590868E-2,-7.392364E-2,-0E0,4.1819744E-2],"split_indices":[1,9,0,0,1,0,0],"split_type":[0,0,0,0,0,0,0],"sum_hessian":[2.9349924E2,2.5257655E2,4.0922665E1,1.8161687E2,7.0959694E1,3.2045025E1,3.8914665E1],"tree_param":{"num_deleted":"0","num_feature":"16","num_nodes":"7","size_leaf_vector":"1"}},{"base_weights":[-6.632025E-3,3.7749696E-1,-1.102601E-1,-0E0,8.964205E-2,-2.1123901E-1,3.880126E-2,4.343357E-2,-2.6292088E-2],"categories":[],"categories_nodes":[],"categories_segments":[],"categories_sizes":[],"default_left":[0,0,0,0,0,0,0,0,0],"id":2,"left_children":[1,3,5,-1,-1,7,-1,-1,-1],"loss_changes":[1.1292692E1,1.2092231E1,1.1750017E1,0E0,0E0,6.7268906E0,0E0,0E0,0E0],"parents":[2147483647,0,0,1,1,2,2,5,5],"right_children":[2,4,6,-1,-1,8,-1,-1,-1],"split_conditions":[-1.3826846E-1,-3.0913474E-2,3.9560413E-1,-0E0,8.964205E-2,-3.4630325E0,3.880126E-2,4.343357E-2,-2.6292088E-2],"split_indices":[3,1,3,0,0,6,0,0,0],"split_type":[0,0,0,0,0,0,0,0,0],"sum_hessian":[2.9866528E2,5.878802E1,2.3987726E2,3.378474E1,2.5003283E1,2.0344609E2,3.643118E1,1.2322776E1,1.911233E2],"tree_param":{"num_deleted":"0","num_feature":"16","num_nodes":"9","size_leaf_vector":"1"}},{"base_weights":[-1.4135888E-2,-5.1554043E-2,6.3405514E-2,2.2891809E-1,-1.1239321E-1,-1.0354886E-2,6.059195E-2,-2.2661548E-2,8.060716E-3],"categories":[],"categories_nodes":[],"categories_segments":[],"categories_sizes":[],"default_left":[0,0,0,0,0,0,0,0,0],"id":3,"left_children":[1,3,-1,5,7,-1,-1,-1,-1],"loss_changes":[6.013403E0,4.639324E0,0E0,6.824456E0,5.785964E0,0E0,0E0,0E0,0E0],"parents":[2147483647,0,0,1,1,3,3,4,4],"right_children":[2,4,-1,6,8,-1,-1,-1,-1],"split_conditions":[1.2595405E-1,-5.21739E-2,6.3405514E-2,-5.714274E-1,2.4203924E-2,-1.0354886E-2,6.059195E-2,-2.2661548E-2,8.060716E-3],"split_indices":[10,10,0,13,10,0,0,0,0],"split_type":[0,0,0,0,0,0,0,0,0],"sum_hessian":[3.0000308E2,2.87083E2,1.29200735E1,4.4529137E1,2.4255386E2,2.0655008E1,2.3874126E1,1.5893578E2,8.361809E1],"tree_param":{"num_deleted":"0","num_feature":"16","num_nodes":"9","size_leaf_vector":"1"}},{"base_weights":[-3.381353E-2,-2.1065846E-1,1.7657802E-1,1.5414225E-1,-3.4397113E-1,-0E0,3.3159214E-1,-2.5309727E-2,4.07404E-2,-4.1695397E-2,2.379881E-2,1.0158937E-1,1.7759021E-2],"categories":[],"categories_nodes":[],"categories_segments":[],"categories_sizes":[],"default_left":[0,0,0,0,0,0,0,0,0,0,0,0,0],"id":4,"left_children":[1,3,5,7,9,-1,11,-1,-1,-1,-1,-1,-1],"loss_changes":[1.1385414E1,8.745845E0,4.372559E0,4.693247E0,6.1982927E0,0E0,5.4593105E0,0E0,0E0,0E0,0E0,0E0,0E0],"parents":[2147483647,0,0,1,1,2,2,3,3,4,4,6,6],"right_children":[2,4,6,8,10,-1,12,-1,-1,-1,-1,-1,-1],"split_conditions":[9.184917E-2,-6.2397156E-2,-2.1178523E-2,-2.7530404E-2,4.3739742E-1,-0E0,-1.3826846E-1,-2.5309727E-2,4.07404E-2,-4.1695397E-2,2.379881E-2,1.0158937E-1,1.7759021E-2],"split_indices":[9,3,15,15,3,0,3,0,0,0,0,0,0],"split_type":[0,0,0,0,0,0,0,0,0,0,0,0,0],"sum_hessian":[3.037837E2,1.7087233E2,1.3291136E2,4.1202114E1,1.2967021E2,5.55097E1,7.7401665E1,1.2489564E1,2.8712553E1,1.1810978E2,1.1560435E1,1.1226088E1,6.617558E1],"tree_param":{"num_deleted":"0","num_feature":"16","num_nodes":"13","size_leaf_vector":"1"}},{"base_weights":[1.2666447E-2,-1.3290507E-2,3.0565423E-1,-0E0,5.2036587E-2],"categories":[],"categories_nodes":[],"categories_segments":[],"categories_sizes":[],"default_left":[0,0,0,0,0],"id":5,"left_children":[1,-1,3,-1,-1],"loss_changes":[1.3100904E1,0E0,6.8191357E0,0E0,0E0],"parents":[2147483647,0,0,2,2],"right_children":[2,-1,4,-1,-1],"split_conditions":[1.02809206E-1,-1.3290507E-2,9.090941E-2,-0E0,5.2036587E-2],"split_indices":[9,0,12,0,0],"split_type":[0,0,0,0,0],"sum_hessian":[2.957619E2,1.9200758E2,1.0375431E2,4.3797066E1,5.9957245E1],"tree_param":{"num_deleted":"0","num_feature":"16","num_nodes":"5","size_leaf_vector":"1"}},{"base_weights":[-7.937616E-4,-7.7358104E-2,6.2372554E-2,3.2863125E-2,-2.0629738E-1,-3.8138438E-2,-0E0],"categories":[],"categories_nodes":[],"categories_segments":[],"categories_sizes":[],"default_left":[0,0,0,0,0,0,0],"id":6,"left_children":[1,3,-1,-1,5,-1,-1],"loss_changes":[1.3010845E1,1.3783598E1,0E0,0E0,7.5073814E0,0E0,0E0],"parents":[2147483647,0,0,1,1,4,4],"right_children":[2,4,-1,-1,6,-1,-1],"split_conditions":[4.433729E-1,-2.0702128E0,6.2372554E-2,3.2863125E-2,9.27176E-3,-3.8138438E-2,-0E0],"split_indices":[3,6,0,0,1,0,0],"split_type":[0,0,0,0,0,0,0],"sum_hessian":[2.955627E2,2.667684E2,2.87943E1,5.9761772E1,2.0700664E2,1.1033862E2,9.6668015E1],"tree_param":{"num_deleted":"0","num_feature":"16","num_nodes":"7","size_leaf_vector":"1"}},{"base_weights":[-0E0,-3.741175E-2,6.630243E-2,-7.100996E-2,4.301453E-2,1.2696231E-2,-1.4086547E-2],"categories":[],"categories_nodes":[],"categories_segments":[],"categories_sizes":[],"default_left":[0,0,0,0,0,0,0],"id":7,"left_children":[1,3,-1,5,-1,-1,-1],"loss_changes":[7.220548E0,3.7289934E0,0E0,3.8833618E0,0E0,0E0,0E0],"parents":[2147483647,0,0,1,1,3,3],"right_children":[2,4,-1,6,-1,-1,-1],"split_conditions":[1.1360805E-1,4.6857333E0,6.630243E-2,-7.6716505E-2,4.301453E-2,1.2696231E-2,-1.4086547E-2],"split_indices":[10,6,0,2,0,0,0],"split_type":[0,0,0,0,0,0,0],"sum_hessian":[3.022427E2,2.870568E2,1.5185937E1,2.724738E2,1.4582994E1,6.327841E1,2.0919537E2],"tree_param":{"num_deleted":"0","num_feature":"16","num_nodes":"7","size_leaf_vector":"1"}},{"base_weights":[5.843598E-3,-7.270749E-2,2.2397324E-2,9.933786E-2,-2.1212302E-1,-3.7149247E-2,3.826672E-2,4.0777344E-3,-3.7465528E-2],"categories":[],"categories_nodes":[],"categories_segments":[],"categories_sizes":[],"default_left":[0,0,0,0,0,0,0,0,0],"id":8,"left_children":[1,3,-1,5,7,-1,-1,-1,-1],"loss_changes":[5.3823133E0,5.227934E0,0E0,1.1653708E1,5.8648305E0,0E0,0E0,0E0,0E0],"parents":[2147483647,0,0,1,1,3,3,4,4],"right_children":[2,4,-1,6,8,-1,-1,-1,-1],"split_conditions":[1.8745027E0,-5.4697584E-2,2.2397324E-2,-2.9574051E-1,-7.677672E-1,-3.7149247E-2,3.826672E-2,4.0777344E-3,-3.7465528E-2],"split_indices":[5,3,0,4,5,0,0,0,0],"split_type":[0,0,0,0,0,0,0,0,0],"sum_hessian":[2.914175E2,2.0721219E2,8.420533E1,8.552348E1,1.216887E2,2.9245808E1,5.6277676E1,4.274578E1,7.894292E1],"tree_param":{"num_deleted":"0","num_feature":"16","num_nodes":"9","size_leaf_vector":"1"}},{"base_weights":[8.635718E-3,2.96023E-1,-5.2992765E-2,-0E0,8.365789E-2,-1.7074635E-2,2.4923673E-2],"categories":[],"categories_nodes":[],"categories_segments":[],"categories_sizes":[],"default_left":[0,0,0,0,0,0,0],"id":9,"left_children":[1,3,5,-1,-1,-1,-1],"loss_changes":[5.7929606E0,8.572424E0,8.429357E0,0E0,0E0,0E0,0E0],"parents":[2147483647,0,0,1,1,2,2],"right_children":[2,4,6,-1,-1,-1,-1],"split_conditions":[-2.0702128E0,-1.2552667E-1,1.1190445E-1,-0E0,8.365789E-2,-1.7074635E-2,2.4923673E-2],"split_indices":[6,2,2,0,0,0,0],"split_type":[0,0,0,0,0,0,0],"sum_hessian":[2.9599545E2,5.867354E1,2.373219E2,3.945893E1,1.921461E1,1.7589218E2,6.1429718E1],"tree_param":{"num_deleted":"0","num_feature":"16","num_nodes":"7","size_leaf_vector":"1"}},{"base_weights":[-1.6641006E-2,-1.1288108E-1,2.5362937E-2,9.480834E-3,-1.8587615E-2],"categories":[],"categories_nodes":[],"categories_segments":[],"categories_sizes":[],"default_left":[0,0,0,0,0],"id":10,"left_children":[1,3,-1,-1,-1],"loss_changes":[7.4703913E0,3.7146611E0,0E0,0E0,0E0],"parents":[2147483647,0,0,1,1],"right_children":[2,4,-1,-1,-1],"split_conditions":[3.6568366E-2,-8.245569E-2,2.5362937E-2,9.480834E-3,-1.8587615E-2],"split_indices":[10,2,0,0,0],"split_type":[0,0,0,0,0],"sum_hessian":[2.9716583E2,2.2571848E2,7.1447365E1,5.1453068E1,1.7426541E2],"tree_param":{"num_deleted":"0","num_feature":"16","num_nodes":"5","size_leaf_vector":"1"}},{"base_weights":[7.6008593E-3,-1.7586624E-2,5.6422777E-2,2.659673E-1,-9.417262E-2,-4.5778337E-3,5.4506656E-2,-1.5605786E-2,2.3162538E-2],"categories":[],"categories_nodes":[],"categories_segments":[],"categories_sizes":[],"default_left":[0,0,0,0,0,0,0,0,0],"id":11,"left_children":[1,3,-1,5,7,-1,-1,-1,-1],"loss_changes":[5.4360833E0,5.6976037E0,0E0,5.855289E0,4.524895E0,0E0,0E0,0E0,0E0],"parents":[2147483647,0,0,1,1,3,3,4,4],"right_children":[2,4,-1,6,8,-1,-1,-1,-1],"split_conditions":[4.6857333E0,-2.3001082E0,5.6422777E-2,5.882696E-2,4.8123185E-2,-4.5778337E-3,5.4506656E-2,-1.5605786E-2,2.3162538E-2],"split_indices":[6,6,0,12,15,0,0,0,0],"split_type":[0,0,0,0,0,0,0,0,0],"sum_hessian":[2.9654395E2,2.8003314E2,1.6510803E1,5.324976E1,2.2678339E2,2.1591366E1,3.1658394E1,1.9594437E2,3.0839024E1],"tree_param":{"num_deleted":"0","num_feature":"16","num_nodes":"9","size_leaf_vector":"1"}},{"base_weights":[8.93441E-3,5.806911E-2,-1.6166285E-2,4.153242E-2,-2.8959664E-2,-1.6117841E-2,1.328038E-2],"categories":[],"categories_nodes":[],"categories_segments":[],"categories_sizes":[],"default_left":[0,0,0,0,0,0,0],"id":12,"left_children":[1,-1,3,5,-1,-1,-1],"loss_changes":[5.551838E0,0E0,5.0044503E0,4.157443E0,0E0,0E0,0E0],"parents":[2147483647,0,0,2,2,3,3],"right_children":[2,-1,4,6,-1,-1,-1],"split_conditions":[-3.4366226E-1,5.806911E-2,6.372571E-1,-3.9594826E-1,-2.8959664E-2,-1.6117841E-2,1.328038E-2],"split_indices":[3,0,7,7,0,0,0],"split_type":[0,0,0,0,0,0,0],"sum_hessian":[2.9488452E2,1.5980077E1,2.7890445E2,2.2394003E2,5.4964405E1,6.2152863E1,1.6178717E2],"tree_param":{"num_deleted":"0","num_feature":"16","num_nodes":"7","size_leaf_vector":"1"}},{"base_weights":[7.238211E-3,-6.328941E-2,2.20592E-2,-3.0035837E-2,7.382725E-4],"categories":[],"categories_nodes":[],"categories_segments":[],"categories_sizes":[],"default_left":[0,0,0,0,0],"id":13,"left_children":[1,3,-1,-1,-1],"loss_changes":[4.839908E0,4.3002853E0,0E0,0E0,0E0],"parents":[2147483647,0,0,1,1],"right_children":[2,4,-1,-1,-1],"split_conditions":[1.17508486E-1,-2.663599E-2,2.20592E-2,-3.0035837E-2,7.382725E-4],"split_indices":[9,15,0,0,0],"split_type":[0,0,0,0,0],"sum_hessian":[2.9519797E2,2.1446475E2,8.073322E1,5.6107647E1,1.583571E2],"tree_param":{"num_deleted":"0","num_feature":"16","num_nodes":"5","size_leaf_vector":"1"}},{"base_weights":[-0E0,-1.2295175E-2,2.251119E-2],"categories":[],"categories_nodes":[],"categories_segments":[],"categories_sizes":[],"default_left":[0,0,0],"id":14,"left_children":[1,-1,-1],"loss_changes":[8.073897E0,0E0,0E0],"parents":[2147483647,0,0],"right_children":[2,-1,-1],"split_conditions":[1.0396717E-1,-1.2295175E-2,2.251119E-2],"split_indices":[9,0,0],"split_type":[0,0,0],"sum_hessian":[2.94431E2,1.9630594E2,9.812507E1],"tree_param":{"num_deleted":"0","num_feature":"16","num_nodes":"3","size_leaf_vector":"1"}},{"base_weights":[-0E0],"categories":[],"categories_nodes":[],"categories_segments":[],"categories_sizes":[],"default_left":[0],"id":15,"left_children":[-1],"loss_changes":[0E0],"parents":[2147483647],"right_children":[-1],"split_conditions":[-0E0],"split_indices":[0],"split_type":[0],"sum_hessian":[2.9226477E2],"tree_param":{"num_deleted":"0","num_feature":"16","num_nodes":"1","size_leaf_vector":"1"}},{"base_weights":[-1.1636372E-2,-9.784408E-3,2.046493E-2],"categories":[],"categories_nodes":[],"categories_segments":[],"categories_sizes":[],"default_left":[0,0,0],"id":16,"left_children":[1,-1,-1],"loss_changes":[5.2697563E0,0E0,0E0],"parents":[2147483647,0,0],"right_children":[2,-1,-1],"split_conditions":[1.19999565E-1,-9.784408E-3,2.046493E-2],"split_indices":[9,0,0],"split_type":[0,0,0],"sum_hessian":[2.9058572E2,2.1510606E2,7.547965E1],"tree_param":{"num_deleted":"0","num_feature":"16","num_nodes":"3","size_leaf_vector":"1"}},{"base_weights":[2.365431E-2,5.5576876E-2,-0E0],"categories":[],"categories_nodes":[],"categories_segments":[],"categories_sizes":[],"default_left":[0,0,0],"id":17,"left_children":[1,-1,-1],"loss_changes":[4.233574E0,0E0,0E0],"parents":[2147483647,0,0],"right_children":[2,-1,-1],"split_conditions":[-3.5134298E-1,5.5576876E-2,-0E0],"split_indices":[3,0,0],"split_type":[0,0,0],"sum_hessian":[2.8675085E2,1.3921238E1,2.7282962E2],"tree_param":{"num_deleted":"0","num_feature":"16","num_nodes":"3","size_leaf_vector":"1"}},{"base_weights":[-0E0,-1.0706834E-2,2.2903772E-2],"categories":[],"categories_nodes":[],"categories_segments":[],"categories_sizes":[],"default_left":[0,0,0],"id":18,"left_children":[1,-1,-1],"loss_changes":[7.2381053E0,0E0,0E0],"parents":[2147483647,0,0],"right_children":[2,-1,-1],"split_conditions":[1.07022166E-1,-1.0706834E-2,2.2903772E-2],"split_indices":[9,0,0],"split_type":[0,0,0],"sum_hessian":[2.9484537E2,2.0366805E2,9.117732E1],"tree_param":{"num_deleted":"0","num_feature":"16","num_nodes":"3","size_leaf_vector":"1"}},{"base_weights":[7.203975E-3],"categories":[],"categories_nodes":[],"categories_segments":[],"categories_sizes":[],"default_left":[0],"id":19,"left_children":[-1],"loss_changes":[0E0],"parents":[2147483647],"right_children":[-1],"split_conditions":[7.1463437E-4],"split_indices":[0],"split_type":[0],"sum_hessian":[2.888698E2],"tree_param":{"num_deleted":"0","num_feature":"16","num_nodes":"1","size_leaf_vector":"1"}},{"base_weights":[-0E0,-2.6218453E-1,5.1189486E-2,1.4325277E-2,-5.16024E-2,4.7710767E-1,-1.2513824E-3,-0E0,7.091426E-2],"categories":[],"categories_nodes":[],"categories_segments":[],"categories_sizes":[],"default_left":[0,0,0,0,0,0,0,0,0],"id":20,"left_children":[1,3,5,-1,-1,7,-1,-1,-1],"loss_changes":[3.8944104E0,5.8215857E0,7.670219E0,0E0,0E0,4.2832613E0,0E0,0E0,0E0],"parents":[2147483647,0,0,1,1,2,2,5,5],"right_children":[2,4,6,-1,-1,8,-1,-1,-1],"split_conditions":[-2.4171731E-1,-6.786922E-2,-1.3410553E-1,1.4325277E-2,-5.16024E-2,-2.6627E-2,-1.2513824E-3,-0E0,7.091426E-2],"split_indices":[4,15,3,0,0,1,0,0,0],"split_type":[0,0,0,0,0,0,0,0,0],"sum_hessian":[2.9090494E2,4.7286114E1,2.4361884E2,1.4977894E1,3.230822E1,3.6278137E1,2.073407E2,1.1779937E1,2.44982E1],"tree_param":{"num_deleted":"0","num_feature":"16","num_nodes":"9","size_leaf_vector":"1"}}]},"name":"gbtree"},"learner_model_param":{"base_score":"[5E-1]","boost_from_average":"1","num_class":"0","num_feature":"16","num_target":"1"},"objective":{"name":"binary:logistic","reg_loss_param":{"scale_pos_weight":"0.192307696"}}},"version":[3,2,0]}